mlflow_cloudsmith-0.0.1.dist-info/licenses/LICENSE
plugin/__init__.py
plugin/cloudsmith_repository.py
scripts/cleanup_orphans.sh
mlflow_cloudsmith-0.0.1.dist-info/METADATA
mlflow_cloudsmith-0.0.1.dist-info/WHEEL
mlflow_cloudsmith-0.0.1.dist-info/entry_points.txt
mlflow_cloudsmith-0.0.1.dist-info/top_level.txt
mlflow_cloudsmith-0.0.1.dist-info/RECORD
