Metadata-Version: 2.4
Name: mlflow-cloudsmith
Version: 0.0.1
Summary: MLflow plugin for storing artifacts in Cloudsmith repositories
Author-email: Cloudsmith Customer Engineering <support@cloudsmith.com>
License: Apache License
Project-URL: Source, https://github.com/cloudsmith-io/mlflow-cloudsmith-plugin
Project-URL: Bug Tracker, https://github.com/cloudsmith-io/mlflow-cloudsmith-plugin/issues
Project-URL: Documentation, https://github.com/cloudsmith-io/mlflow-cloudsmith-plugin#readme
Classifier: Development Status :: 3 - Alpha
Classifier: Programming Language :: Python :: 3
Requires-Python: >=3.8
License-File: LICENSE
Requires-Dist: requests>=2.25.0
Requires-Dist: mlflow>=2.12.0
Provides-Extra: dev
Requires-Dist: pytest>=6.0; extra == "dev"
Requires-Dist: pytest-cov>=2.0; extra == "dev"
Requires-Dist: black>=22.0; extra == "dev"
Requires-Dist: flake8>=4.0; extra == "dev"
Requires-Dist: mypy>=0.950; extra == "dev"
Requires-Dist: build>=1.0.0; extra == "dev"
Provides-Extra: test
Requires-Dist: pytest>=6.0; extra == "test"
Requires-Dist: pytest-cov>=2.0; extra == "test"
Dynamic: license-file
